{"P-008613": "NÁŘADÍ OSTATNÍ Řezačka otvorů do plechu HC1 EV 26795", "P-008687": "OPP Štípenkový opasek", "P-008733": "OPP Tesařská dvojitá brašna", "P-008734": "OPP Tesařská kapsa zdvojená COL-040R oranžová", "P-008735": "OPP Tesařská kapsa zdvojená přírodní barva", "P-008736": "OPP Tesařská kapsa zdvojená černá", "P-010079": "COLEMAN Paletová rampa -", "P-053440": "NÁŘADÍ OSTATNÍ Páčidlo nastavitelné 209 SB/25 824115", "P-056780": "NÁŘADÍ OSTATNÍ Pojízdná hliníková rampa DZV400", "P-056781": "NÁŘADÍ OSTATNÍ Kleště na střešní tašku DZZ 2-400", "P-056789": "NÁŘADÍ OSTATNÍ Kleště na střešní krytinu 01.02.00005", "P-056910": "NÁŘADÍ OSTATNÍ Automatická tužka Pica Dry 3030", "P-024508": "OPP Bezpečnostní obuv Gear Solid Vapor S3 SG80003", "P-046043": "FREUND  brašna na hřebíky 06023000", "P-051288": "OPP Rukavice pro mechaniky - velikost 10 40877-6", "P-047156": "OPP Bezpečnostní obuv Gear Solid Falcon S3 SG73002", "P-050780": "YATO  taška na nářadí YT-74372", "P-051287": "OPP Rukavice pro mechaniky - velikost 9 40876-6", "P-052651": "OPP Rukavice pro mechaniky - velikost 11 42980-6", "P-008070": "FREUND  kladivo na břidlici - pravé 00020650", "P-008105": "FREUND  nůžky na plech kroužkové - pravé 275 mm 01224275", "P-008086": "FREUND  falcovací kleště zahnuté 90° - 80 mm 01092080", "P-008104": "FREUND  nůžky na plech výstřihové - levé 250 mm 01223250", "P-008110": "FREUND  nůžky na plech pelikánky - pravé 350 mm 01230350", "P-008112": "FREUND  nůžky pákové na břidlici 00350000", "P-027895": "FREUND  ohýbačka háků 60 cm 01000600", "P-008072": "FREUND  kladivo na břidlici - levé 00021650", "P-008077": "FREUND  falcovací kleště rovné - 40 mm 01080040", "P-008128": "FREUND  nůžky na vláknocementové šablony 800 mm 00960000", "P-008071": "FREUND  tesařské kladivo s magnetem 00112001", "P-008106": "FREUND  nůžky na plech kroužkové - levé 275 mm 01225275", "P-008107": "FREUND  nůžky na plech pelikánky - pravé 300 mm 01230300", "P-019413": "FREUND  hrdlovačka/roztahovák svodů 100 mm 01320100", "P-008130": "FREUND  ohýbačka háků 80 cm 01000800", "P-008078": "FREUND  falcovací kleště zahnuté 45° - 40 mm 01090040", "P-008103": "FREUND  nůžky na plech výstřihové - pravé 250 mm 01222250", "P-008111": "FREUND  nůžky na plech výstřihové - pravé 275 mm 01222275", "P-020513": "FREUND  rýsovací šablona 01132000", "P-023290": "DEN BRAVEN Pistole rámová COX-HKS 12 N110", "P-008074": "FREUND  tesařské kladivo s magnetem a koženou rukojetí 00114000", "P-008085": "FREUND  falcovací kleště zahnuté 90° - 60 mm 01092060", "P-008117": "FREUND  nůž k rýhování vláknocementu 05610000", "P-019691": "FREUND  kleště pro narovnání falců 01070250", "P-008080": "FREUND  falcovací kleště rovné - 60 mm 01080060", "P-008083": "FREUND  falcovací kleště zahnuté 45° - 80 mm 01090080", "P-008123": "FREUND  tesařská brnkačka 30 m 03020000", "P-008126": "FREUND  lamač břidlice 30 x 6 mm oblouk 00311000", "P-023065": "FREUND  nůžky na plech pelikánky - levé 300 mm 01231300", "P-025777": "FREUND  sada pro ukončení falcu na hraně 91190000", "P-008108": "FREUND  nůžky na eternit ERGO CUT 00920000", "P-018861": "FREUND  trhačka hřebíků 600 mm 00240600", "P-008082": "FREUND  falcovací kleště zahnuté 45° - 60 mm 01090060", "P-008081": "FREUND  falcovací kleště rovné - 80 mm 01080080", "P-008084": "FREUND  falcovací kleště zahnuté 90° - 40 mm 01092040", "P-008122": "FREUND  měřič rozteče latí 15-40 cm 00380000", "P-008124": "FREUND  vodováha/libela provázková 01890001", "P-021269": "FREUND  drážkovnice/šlajsna 100 mm 01150100", "P-021769": "FREUND  ohýbač úhlové drážky 91101000", "P-025773": "FREUND  ohýbačka okapní hrany 250 mm 91070000", "P-019692": "FREUND  falcovací kleště stlačovací 01100080", "P-020582": "FREUND  ohýbačka plechu 300 mm 91050000", "P-025782": "FREUND  uzavírač úhlové drážky (ve stoje) 91171000", "P-029111": "FREUND  ohýbací kleště s rovnými čelistmi 180 mm 01141180", "P-025781": "FREUND  ohýbačka úhlové drážky/falcu 91170000", "P-027885": "FREUND  ohýbačka kapes 140 mm 01130000", "P-025778": "FREUND  uzavírač dvojité drážky (oblouk) 65 mm 91180000", "P-028410": "FREUND  ohýbačka plechu 101 BG 1000 mm 91030000", "P-029110": "FREUND  klempířské kleště děrovací 00360010", "P-045553": "OPP Sada pro práci ve výškách Set ECO - EvoBelt Set ECO - EvoBelt", "P-051077": "OPP Lanostop - zachycovač pádu, délka 20 m XPFAAC032", "P-051946": "YATO  kleště kombinované 200 mm YT-2008", "P-048620": "YATO  ohýbačka žlabových háků 630 mm YT-5410", "P-029125": "FREUND  nůžky na plech Berlínské - pravé HRC 01210250", "P-030217": "FREUND  nůžky na plech výstřihové 35 - 300 mm 00371000", "P-029114": "FREUND  kleště se zakulacenou špičkou - 240 mm 01360240", "P-029116": "FREUND  nůžky figurální - levé 250 mm 01271250", "P-029134": "FREUND  nůžky na plech pelikánky - pravé 300 mm 01235300", "P-033185": "FREUND  falcovací kleště MINI 45° 22 mm 01090022", "P-033186": "FREUND  plastová špičatá palička 550 g 01674000", "P-030216": "FREUND  sada falcovacích kleští 60 mm - 0°, 45°a 90° 04670058", "P-032054": "FREUND  dřevěná palička 560 g, průměr 70 mm 01677000", "P-033193": "FREUND  vsazovač filcu 01131000", "P-029112": "FREUND  ohýbací kleště ohnuté - 160 mm 01161160", "P-032055": "FREUND  klempířské kleště krepovací - 30 mm 01320002", "P-033189": "FREUND  nůžky na plech výstřihové - levé HRc 01221250", "P-036222": "FREUND  měřič rozteče latí do 40 cm 00382000", "P-036344": "FREUND  ohýbací kleště zkosené z jedné strany - 180 mm 01141181", "P-036345": "FREUND  falcovací stlačovací kleště s N kloubem 01100081", "P-043376": "FREUND  nůžky na eternit MASTERCUT 00950000", "P-029113": "FREUND  ohýbací kleště ohnuté - 180 mm 01161180", "P-029115": "FREUND  nůžky figurální - pravé 250 mm 01270250", "P-036178": "FREUND  tesařská brnkačka 30 m 03032000", "P-036377": "FREUND  nůž na řezání střešní lepenky zahnutý 02510000", "P-029133": "FREUND  falcovací rovné kleště s potaženou rukojetí - 60 mm 01081060", "P-033187": "FREUND  klempířské kleště k vyrovnání žlabů 01010000", "P-033188": "FREUND  nůžky na plech výstřihové - pravé HRc 01220250", "P-036341": "FREUND  nylonová palička - průměr 32 mm 01670032", "P-036342": "FREUND  obrubovací kleště - úzké a ploché 01370240", "P-035568": "FREUND  měřič rozteče latí do 55 cm 00383000", "P-041052": "FREUND  drážkovnice hranatá - 140 mm 01110000", "P-043500": "FREUND  nůžky přímé zahnuté 90° - pravé 01296200", "P-043501": "FREUND  nůžky přímé zahnuté 90° - levé 01297200", "P-045335": "FREUND  falcovací kleště MINI - rovné 22 mm 01080022", "P-045334": "FREUND  falcovací kleště na dvojitou drážkou s čelistmi z PVC 92170000", "P-045336": "FREUND  přítlačný váleček ERGOWHEEL 04210045", "P-045445": "FREUND  nůžky Ideal - pravé 260 mm 01250260", "P-045407": "FREUND  sada tří nůžek z nerezové oceli - pravé, levé, pravé pelikánky 04670075", "P-046122": "FREUND  lopatka pro odstranění šindelové krytiny 00270000", "P-045412": "FREUND  řezačka na bobrovku 400 mm 00260000", "P-046044": "FREUND  plastové kladivo 550 g 01678145", "P-046121": "FREUND  lopatka na šindelovou krytinu 00271000", "P-044264": "FREUND  trhačka hřebíků 475 mm 00240470", "P-045288": "FREUND  páčidlo / uvolňovač střešních latí 00250000", "P-045794": "FREUND  nůž/řezák střešních folií 02140000", "P-045446": "FREUND  nůžky Ideal - levé 260 mm 01251260", "P-053139": "FREUND  posuvný úhelník 300 mm 01841300", "PL-004524|NEUTR": "NÁŘADÍ OSTATNÍ Hrdlovačka/roztahovák svodů 80 mm 7794362.01", "P-056732": "YATO  klempířské kleště - rovné 60 mm YT-5415", "P-056735": "YATO  uzavírač dvojité drážky YT-5402", "P-056733": "YATO  klempířské kleště 45° - 60 mm YT-5416", "PL-004526|NEUTR": "NÁŘADÍ OSTATNÍ Hrdlovačka/roztahovák svodů 120 mm", "PL-004525|NEUTR": "NÁŘADÍ OSTATNÍ Hrdlovačka/roztahovák svodů 100 mm 7794363.01", "PL-004527|NEUTR": "NÁŘADÍ OSTATNÍ Hydroizolatérské nářadí - Vysoušeč vody molitanový", "PL-001040|NEUTR": "IKO BELGICKÉ Nářadí IKO - Lopata na odstranění šindele 74210018"}